kskimtestmodule/__init__.py
kskimtestmodule/circle.py
kskimtestmodule/rectangle.py
kskimtestmodule/testfunc.py
kskimtestmodule/testspark.py
kskimtestmodule2/__init__.py
kskimtestmodule2/circle.py
kskimtestmodule2/rectangle.py
kskimtestmodule2/testfunc.py
kskimtestmodule2/testspark.py
kskimtestmodule3/__init__.py
kskimtestmodule3/circle.py
kskimtestmodule3/rectangle.py
kskimtestmodule3/testfunc.py
kskimtestmodule3/testspark.py
kskimtestmodule2-0.0.2.dist-info/LICENSE
kskimtestmodule2-0.0.2.dist-info/METADATA
kskimtestmodule2-0.0.2.dist-info/WHEEL
kskimtestmodule2-0.0.2.dist-info/top_level.txt
kskimtestmodule2-0.0.2.dist-info/RECORD
