Metadata-Version: 2.1
Name: kskimtestmodule2
Version: 0.0.2
Summary: A simple Python library for test spark in zeppelin
Author: kisun3.kim
License-File: LICENSE
